LICENSE
MANIFEST.in
README.rst
setup.py
asqlite3/__init__.py
asqlite3/conn.py
asqlite3/usefuls.py
asqlite3.egg-info/PKG-INFO
asqlite3.egg-info/SOURCES.txt
asqlite3.egg-info/dependency_links.txt
asqlite3.egg-info/top_level.txt