Metadata-Version: 1.1
Name: asqlite3
Version: 0.0.1
Summary: An async sqlite3 module
Home-page: https://github.com/try-fail1/asqlite3
Author: Ryan Vink
Author-email: ryantvink@gmail.com
License: MIT
Keywords: sql,sqlite3,asyncio
Platform: UNKNOWN
Classifier: Development Status :: 5 - Production/Stable
Classifier: Framework :: AsyncIO
Classifier: Intended Audience :: Developers
Classifier: License :: OSI Approved :: MIT License
Classifier: Topic :: Software Development :: Libraries
